MANIFEST.in
README.rst
plz_draw
setup.py
pyGeoDb.egg-info/PKG-INFO
pyGeoDb.egg-info/SOURCES.txt
pyGeoDb.egg-info/dependency_links.txt
pyGeoDb.egg-info/top_level.txt
pygeodb/__init__.py
pygeodb/borderdata.py
pygeodb/plzdata.py
pygeodb/pygeodb_core.py
pygeodb/voronoi.py