Metadata-Version: 1.0
Name: pyGeoDb
Version: 1.3
Summary: distance calculation based on ZIP codes and map generation
Home-page: http://github.com/mdornseif/pyGeoDb
Author: Maximillian Dornseif
Author-email: md@hudora.de
License: UNKNOWN
Platform: UNKNOWN
Classifier: License :: OSI Approved :: BSD License
Classifier: Intended Audience :: Developers
Classifier: Programming Language :: Python
